camelsde/__init__.py
camelsde/config.py
camelsde/models.py
camelsde-0.2.0.dist-info/METADATA
camelsde-0.2.0.dist-info/WHEEL
camelsde-0.2.0.dist-info/licenses/LICENSE
camelsde-0.2.0.dist-info/RECORD
