Metadata-Version: 2.4
Name: camelsde
Version: 0.2.0
Summary: Python package for working with the CAMELS-DE dataset
Project-URL: Homepage, https://github.com/AlexDo1/camelsde
Project-URL: Bug Tracker, https://github.com/AlexDo1/camelsde/issues
Author: alexander.dolich@kit.edu
License: Creative Commons Legal Code
License-File: LICENSE
Classifier: Development Status :: 4 - Beta
Classifier: Intended Audience :: Science/Research
Classifier: License :: OSI Approved :: MIT License
Classifier: Operating System :: OS Independent
Classifier: Programming Language :: Python :: 3
Classifier: Topic :: Scientific/Engineering :: Hydrology
Requires-Python: >=3.8
Requires-Dist: geopandas
Requires-Dist: pandas
Requires-Dist: platformdirs>=3.0.0
Requires-Dist: plotly
Requires-Dist: polars
Requires-Dist: pyarrow
Requires-Dist: pydantic-settings>=2.0.0
Requires-Dist: pydantic>=2.0.0
